Metadata-Version: 1.1
Name: stacks-summary
Version: 1.0
Summary: Stacks reports generator
Home-page: https://github.com/mariabernard/galaxy_wrappers
Author: Maria Bernard
Author-email: maria.bernard@inra.fr
License: MIT
Platform: Posix; MacOS X; Windows
Classifier: Development Status :: 3 - Alpha
Classifier: Intended Audience :: Developers
Classifier: License :: OSI Approved :: GNU General Public License v3 or later (GPLv3+)
Classifier: Operating System :: OS Independent
Classifier: Topic :: Scientific/Engineering
Classifier: Programming Language :: Python :: 2
Classifier: Programming Language :: Python :: 2.6
Classifier: Programming Language :: Python :: 2.7
